{"nodes": [{"id": "users_sandyagu_desktop_simcity_axl_api_recv_go", "label": "recv.go", "file_type": "code", "source_file": "/Users/sandyagu/Desktop/simcity/axl/api/recv.go", "source_location": "L1"}, {"id": "api_receivedmessage", "label": "ReceivedMessage", "file_type": "code", "source_file": "/Users/sandyagu/Desktop/simcity/axl/api/recv.go", "source_location": "L9"}, {"id": "api_receivedqueue", "label": "receivedQueue", "file_type": "code", "source_file": "/Users/sandyagu/Desktop/simcity/axl/api/recv.go", "source_location": "L14"}, {"id": "api_recv_newreceivedqueue", "label": "newReceivedQueue()", "file_type": "code", "source_file": "/Users/sandyagu/Desktop/simcity/axl/api/recv.go", "source_location": "L20"}, {"id": "api_receivedqueue_push", "label": ".Push()", "file_type": "code", "source_file": "/Users/sandyagu/Desktop/simcity/axl/api/recv.go", "source_location": "L24"}, {"id": "api_receivedqueue_pop", "label": ".Pop()", "file_type": "code", "source_file": "/Users/sandyagu/Desktop/simcity/axl/api/recv.go", "source_location": "L33"}, {"id": "api_receivedqueue_reset", "label": ".Reset()", "file_type": "code", "source_file": "/Users/sandyagu/Desktop/simcity/axl/api/recv.go", "source_location": "L44"}, {"id": "api_receivedqueue_len", "label": ".Len()", "file_type": "code", "source_file": "/Users/sandyagu/Desktop/simcity/axl/api/recv.go", "source_location": "L50"}, {"id": "api_receivedqueue_snapshot", "label": ".Snapshot()", "file_type": "code", "source_file": "/Users/sandyagu/Desktop/simcity/axl/api/recv.go", "source_location": "L56"}, {"id": "api_recv_handlerecv", "label": "HandleRecv()", "file_type": "code", "source_file": "/Users/sandyagu/Desktop/simcity/axl/api/recv.go", "source_location": "L67"}], "edges": [{"source": "users_sandyagu_desktop_simcity_axl_api_recv_go", "target": "go_pkg_net_http", "relation": "imports_from", "confidence": "EXTRACTED", "source_file": "/Users/sandyagu/Desktop/simcity/axl/api/recv.go", "source_location": "L4", "weight": 1.0}, {"source": "users_sandyagu_desktop_simcity_axl_api_recv_go", "target": "go_pkg_sync", "relation": "imports_from", "confidence": "EXTRACTED", "source_file": "/Users/sandyagu/Desktop/simcity/axl/api/recv.go", "source_location": "L5", "weight": 1.0}, {"source": "users_sandyagu_desktop_simcity_axl_api_recv_go", "target": "api_receivedmessage", "relation": "contains", "confidence": "EXTRACTED", "source_file": "/Users/sandyagu/Desktop/simcity/axl/api/recv.go", "source_location": "L9", "weight": 1.0}, {"source": "users_sandyagu_desktop_simcity_axl_api_recv_go", "target": "api_receivedqueue", "relation": "contains", "confidence": "EXTRACTED", "source_file": "/Users/sandyagu/Desktop/simcity/axl/api/recv.go", "source_location": "L14", "weight": 1.0}, {"source": "users_sandyagu_desktop_simcity_axl_api_recv_go", "target": "api_recv_newreceivedqueue", "relation": "contains", "confidence": "EXTRACTED", "source_file": "/Users/sandyagu/Desktop/simcity/axl/api/recv.go", "source_location": "L20", "weight": 1.0}, {"source": "api_receivedqueue", "target": "api_receivedqueue_push", "relation": "method", "confidence": "EXTRACTED", "source_file": "/Users/sandyagu/Desktop/simcity/axl/api/recv.go", "source_location": "L24", "weight": 1.0}, {"source": "api_receivedqueue", "target": "api_receivedqueue_pop", "relation": "method", "confidence": "EXTRACTED", "source_file": "/Users/sandyagu/Desktop/simcity/axl/api/recv.go", "source_location": "L33", "weight": 1.0}, {"source": "api_receivedqueue", "target": "api_receivedqueue_reset", "relation": "method", "confidence": "EXTRACTED", "source_file": "/Users/sandyagu/Desktop/simcity/axl/api/recv.go", "source_location": "L44", "weight": 1.0}, {"source": "api_receivedqueue", "target": "api_receivedqueue_len", "relation": "method", "confidence": "EXTRACTED", "source_file": "/Users/sandyagu/Desktop/simcity/axl/api/recv.go", "source_location": "L50", "weight": 1.0}, {"source": "api_receivedqueue", "target": "api_receivedqueue_snapshot", "relation": "method", "confidence": "EXTRACTED", "source_file": "/Users/sandyagu/Desktop/simcity/axl/api/recv.go", "source_location": "L56", "weight": 1.0}, {"source": "users_sandyagu_desktop_simcity_axl_api_recv_go", "target": "api_recv_handlerecv", "relation": "contains", "confidence": "EXTRACTED", "source_file": "/Users/sandyagu/Desktop/simcity/axl/api/recv.go", "source_location": "L67", "weight": 1.0}, {"source": "api_receivedqueue_push", "target": "api_receivedqueue_len", "relation": "calls", "confidence": "EXTRACTED", "source_file": "/Users/sandyagu/Desktop/simcity/axl/api/recv.go", "source_location": "L27", "weight": 1.0}, {"source": "api_receivedqueue_pop", "target": "api_receivedqueue_len", "relation": "calls", "confidence": "EXTRACTED", "source_file": "/Users/sandyagu/Desktop/simcity/axl/api/recv.go", "source_location": "L36", "weight": 1.0}, {"source": "api_receivedqueue_snapshot", "target": "api_receivedqueue_len", "relation": "calls", "confidence": "EXTRACTED", "source_file": "/Users/sandyagu/Desktop/simcity/axl/api/recv.go", "source_location": "L59", "weight": 1.0}, {"source": "api_recv_handlerecv", "target": "api_receivedqueue_pop", "relation": "calls", "confidence": "EXTRACTED", "source_file": "/Users/sandyagu/Desktop/simcity/axl/api/recv.go", "source_location": "L68", "weight": 1.0}], "raw_calls": [{"caller_nid": "api_receivedqueue_push", "callee": "Lock", "is_member_call": true, "source_file": "/Users/sandyagu/Desktop/simcity/axl/api/recv.go", "source_location": "L25"}, {"caller_nid": "api_receivedqueue_push", "callee": "Unlock", "is_member_call": true, "source_file": "/Users/sandyagu/Desktop/simcity/axl/api/recv.go", "source_location": "L26"}, {"caller_nid": "api_receivedqueue_push", "callee": "append", "is_member_call": false, "source_file": "/Users/sandyagu/Desktop/simcity/axl/api/recv.go", "source_location": "L30"}, {"caller_nid": "api_receivedqueue_pop", "callee": "Lock", "is_member_call": true, "source_file": "/Users/sandyagu/Desktop/simcity/axl/api/recv.go", "source_location": "L34"}, {"caller_nid": "api_receivedqueue_pop", "callee": "Unlock", "is_member_call": true, "source_file": "/Users/sandyagu/Desktop/simcity/axl/api/recv.go", "source_location": "L35"}, {"caller_nid": "api_receivedqueue_reset", "callee": "Lock", "is_member_call": true, "source_file": "/Users/sandyagu/Desktop/simcity/axl/api/recv.go", "source_location": "L45"}, {"caller_nid": "api_receivedqueue_reset", "callee": "Unlock", "is_member_call": true, "source_file": "/Users/sandyagu/Desktop/simcity/axl/api/recv.go", "source_location": "L46"}, {"caller_nid": "api_receivedqueue_len", "callee": "Lock", "is_member_call": true, "source_file": "/Users/sandyagu/Desktop/simcity/axl/api/recv.go", "source_location": "L51"}, {"caller_nid": "api_receivedqueue_len", "callee": "Unlock", "is_member_call": true, "source_file": "/Users/sandyagu/Desktop/simcity/axl/api/recv.go", "source_location": "L52"}, {"caller_nid": "api_receivedqueue_len", "callee": "len", "is_member_call": false, "source_file": "/Users/sandyagu/Desktop/simcity/axl/api/recv.go", "source_location": "L53"}, {"caller_nid": "api_receivedqueue_snapshot", "callee": "Lock", "is_member_call": true, "source_file": "/Users/sandyagu/Desktop/simcity/axl/api/recv.go", "source_location": "L57"}, {"caller_nid": "api_receivedqueue_snapshot", "callee": "Unlock", "is_member_call": true, "source_file": "/Users/sandyagu/Desktop/simcity/axl/api/recv.go", "source_location": "L58"}, {"caller_nid": "api_receivedqueue_snapshot", "callee": "make", "is_member_call": false, "source_file": "/Users/sandyagu/Desktop/simcity/axl/api/recv.go", "source_location": "L59"}, {"caller_nid": "api_receivedqueue_snapshot", "callee": "copy", "is_member_call": false, "source_file": "/Users/sandyagu/Desktop/simcity/axl/api/recv.go", "source_location": "L60"}, {"caller_nid": "api_recv_handlerecv", "callee": "WriteHeader", "is_member_call": true, "source_file": "/Users/sandyagu/Desktop/simcity/axl/api/recv.go", "source_location": "L70"}, {"caller_nid": "api_recv_handlerecv", "callee": "Set", "is_member_call": true, "source_file": "/Users/sandyagu/Desktop/simcity/axl/api/recv.go", "source_location": "L75"}, {"caller_nid": "api_recv_handlerecv", "callee": "Header", "is_member_call": true, "source_file": "/Users/sandyagu/Desktop/simcity/axl/api/recv.go", "source_location": "L75"}, {"caller_nid": "api_recv_handlerecv", "callee": "Set", "is_member_call": true, "source_file": "/Users/sandyagu/Desktop/simcity/axl/api/recv.go", "source_location": "L76"}, {"caller_nid": "api_recv_handlerecv", "callee": "Header", "is_member_call": true, "source_file": "/Users/sandyagu/Desktop/simcity/axl/api/recv.go", "source_location": "L76"}, {"caller_nid": "api_recv_handlerecv", "callee": "Write", "is_member_call": true, "source_file": "/Users/sandyagu/Desktop/simcity/axl/api/recv.go", "source_location": "L77"}]}